nexusmaker/CognateParser.py
nexusmaker/__init__.py
nexusmaker/cldf.py
nexusmaker/maker.py
nexusmaker/tools.py
nexusmaker/tests/__init__.py
nexusmaker/tests/conftest.py
nexusmaker/tests/test_CognateParser.py
nexusmaker/tests/test_Complex.py
nexusmaker/tests/test_Mayan.py
nexusmaker/tests/test_NexusMaker.py
nexusmaker/tests/test_NexusMakerAsc.py
nexusmaker/tests/test_NexusMakerAscParam.py
nexusmaker/tests/test_Record.py
nexusmaker/tests/test_cldf.py
nexusmaker/tests/test_example.py
nexusmaker/tests/test_regressions.py
nexusmaker/tests/test_remove_combining_cognates.py
nexusmaker/tests/test_tng.py
nexusmaker/tests/test_tools.py
nexusmaker/tests/test-cldf/Wordlist-metadata.json
nexusmaker/tests/test-cldf/cognates.csv
nexusmaker/tests/test-cldf/languages.csv
nexusmaker/tests/test-cldf/parameters.csv
nexusmaker/tests/test-cldf/values.csv
nexusmaker-2.0.6.dist-info/METADATA
nexusmaker-2.0.6.dist-info/WHEEL
nexusmaker-2.0.6.dist-info/licenses/LICENSE
nexusmaker-2.0.6.dist-info/RECORD
