Metadata-Version: 2.4
Name: nexusmaker
Version: 2.0.6
Summary: nexusmaker - Nexus file maker for language phylogenies
Author-email: "Simon J. Greenhill" <simon@simon.net.nz>
License-Expression: MIT AND (Apache-2.0 OR BSD-2-Clause)
License-File: LICENSE
Requires-Python: >=3.13
Requires-Dist: pycldf
Requires-Dist: python-nexus
